taurus/__init__.py
taurus/client/__init__.py
taurus/client/json_encoder.py
taurus/demo/__init__.py
taurus/demo/cake.py
taurus/demo/measurement_example.py
taurus/demo/strehlow_and_cook.pif
taurus/demo/strehlow_and_cook.py
taurus/demo/strehlow_and_cook_small.pif
taurus/demo/toothpick.jpg
taurus/entity/__init__.py
taurus/entity/base_entity.py
taurus/entity/case_insensitive_dict.py
taurus/entity/dict_serializable.py
taurus/entity/file_link.py
taurus/entity/link_by_uid.py
taurus/entity/setters.py
taurus/entity/util.py
taurus/entity/valid_list.py
taurus/entity/attribute/__init__.py
taurus/entity/attribute/base_attribute.py
taurus/entity/attribute/condition.py
taurus/entity/attribute/parameter.py
taurus/entity/attribute/property.py
taurus/entity/attribute/property_and_conditions.py
taurus/entity/bounds/__init__.py
taurus/entity/bounds/base_bounds.py
taurus/entity/bounds/categorical_bounds.py
taurus/entity/bounds/composition_bounds.py
taurus/entity/bounds/integer_bounds.py
taurus/entity/bounds/real_bounds.py
taurus/entity/object/__init__.py
taurus/entity/object/base_object.py
taurus/entity/object/has_conditions.py
taurus/entity/object/has_parameters.py
taurus/entity/object/has_properties.py
taurus/entity/object/has_quantities.py
taurus/entity/object/has_source.py
taurus/entity/object/has_template.py
taurus/entity/object/ingredient_run.py
taurus/entity/object/ingredient_spec.py
taurus/entity/object/material_run.py
taurus/entity/object/material_spec.py
taurus/entity/object/measurement_run.py
taurus/entity/object/measurement_spec.py
taurus/entity/object/process_run.py
taurus/entity/object/process_spec.py
taurus/entity/source/__init__.py
taurus/entity/source/performed_source.py
taurus/entity/template/__init__.py
taurus/entity/template/attribute_template.py
taurus/entity/template/base_template.py
taurus/entity/template/condition_template.py
taurus/entity/template/has_condition_templates.py
taurus/entity/template/has_parameter_templates.py
taurus_citrine-0.6.0.dist-info/LICENSE
taurus_citrine-0.6.0.dist-info/METADATA
taurus_citrine-0.6.0.dist-info/WHEEL
taurus_citrine-0.6.0.dist-info/top_level.txt
taurus_citrine-0.6.0.dist-info/RECORD
