Metadata-Version: 2.1
Name: taurus-citrine
Version: 0.6.0
Summary: Python library for the Citrine Platform
Home-page: http://github.com/CitrineInformatics/taurus
Author: Max Hutchinson
Author-email: maxhutch@citrine.io
License: UNKNOWN
Platform: UNKNOWN
Requires-Dist: toolz
Requires-Dist: pytest (>=4.3)
Requires-Dist: enum34
Requires-Dist: pint (>=0.9)
Requires-Dist: strip-hints (>=0.1.5)
Requires-Dist: deprecation (<3,>=2.0.7)
